iotrelay_pywws.py
iotrelay_pywws-1.0.2.dist-info/DESCRIPTION.rst
iotrelay_pywws-1.0.2.dist-info/METADATA
iotrelay_pywws-1.0.2.dist-info/RECORD
iotrelay_pywws-1.0.2.dist-info/WHEEL
iotrelay_pywws-1.0.2.dist-info/entry_points.txt
iotrelay_pywws-1.0.2.dist-info/metadata.json
iotrelay_pywws-1.0.2.dist-info/top_level.txt
