Metadata-Version: 2.0
Name: iotrelay-pywws
Version: 1.0.2
Summary: pywws source module for iotrelay
Home-page: https://github.com/eman/iotrelay-pywws
Author: Emmanuel Levijarvi
Author-email: emansl@gmail.com
License: BSD
Keywords: weather IoT
Platform: UNKNOWN
Classifier: Development Status :: 4 - Beta
Classifier: Intended Audience :: Developers
Classifier: Topic :: Utilities
Classifier: License :: OSI Approved :: BSD License
Classifier: Operating System :: OS Independent
Classifier: Programming Language :: Python :: 2
Classifier: Programming Language :: Python :: 3
Requires-Dist: iotrelay
Requires-Dist: pywws
